{
"B89EBF63-05D9-451D-BD64-6D1FA3ED6DA1" : {
"scrollOrigin" : "{-8438, -68}",
"zoomValue" : 1.6388370768658529
},
"B90B303A-10CE-4434-AA00-833ABE589513" : {
"scrollOrigin" : "{455, 356}",
"zoomValue" : 1
},
"SMConfigs2" : "{\"scale\":\"1\",\"unit\":\"px\",\"colorFormat\":\"color-hex\",\"timestamp\":1553283702823}",
"8FCF23B3-9E9D-464D-8886-288AD8682B3D" : {
"scrollOrigin" : "{-1100, 249}",
"zoomValue" : 0.33512533667800282
},
"17E18574-2922-47AD-8B66-56DF4B3B0AC8" : {
"scrollOrigin" : "{-930, 239}",
"zoomValue" : 0.81209097033856636
},
"9BB2D30B-EC4D-4DBB-A516-A0E812DF4838" : {
"scrollOrigin" : "{338, 401}",
"zoomValue" : 1.0737076720342229
},
"document" : {
"pageListHeight" : 250,
"pageListCollapsed" : 0
},
"D7699A0D-654E-4FBB-83DA-BD4C8CA8E26F" : {
"scrollOrigin" : "{-401, -30}",
"zoomValue" : 0.28156475996886787
},
"2496C91D-1E61-482B-8FE6-ABA825AB2079" : {
"scrollOrigin" : "{354, 334}",
"zoomValue" : 0.46654432819824582
}
}